test_first_tz/__init__.py
test_first_tz/poetry.lock
test_first_tz/pyproject.toml
test_first_tz/src/__init__.py
test_first_tz/src/test_first_tz/__init__.py
test_first_tz/src/test_first_tz/shapes.py
test_first_tz-0.1.0.dist-info/METADATA
test_first_tz-0.1.0.dist-info/WHEEL
test_first_tz-0.1.0.dist-info/RECORD
